simulation_engine/__init__.py
simulation_engine/simulation_engine.py
simulation_engine-1.0.1.dist-info/METADATA
simulation_engine-1.0.1.dist-info/WHEEL
simulation_engine-1.0.1.dist-info/top_level.txt
simulation_engine-1.0.1.dist-info/RECORD
